pixel_font_build_tools/__init__.py
pixel_font_build_tools/context.py
pixel_font_build_tools/utils/__init__.py
pixel_font_build_tools/utils/fs_util.py
pixel_font_build_tools/utils/glyph_util.py
pixel_font_build_tools-0.0.2.dist-info/METADATA
pixel_font_build_tools-0.0.2.dist-info/WHEEL
pixel_font_build_tools-0.0.2.dist-info/licenses/LICENSE
pixel_font_build_tools-0.0.2.dist-info/RECORD
